{
  "parent": "gamedataSenseShape_Record",
  "name": "gamedataCone_Record",
  "flags": 66,
  "funcs": [
    {
      "fullName": "Position1",
      "shortName": "Position1",
      "return": {
        "type": "Vector3",
        "flags": 64
      },
      "index": 8357,
      "flags": 1
    },
    {
      "fullName": "Position2",
      "shortName": "Position2",
      "return": {
        "type": "Vector3",
        "flags": 64
      },
      "index": 8356,
      "flags": 1
    },
    {
      "fullName": "Radius1",
      "shortName": "Radius1",
      "return": {
        "type": "Float",
        "flags": 64
      },
      "index": 8358,
      "flags": 1
    },
    {
      "fullName": "Radius2",
      "shortName": "Radius2",
      "return": {
        "type": "Float",
        "flags": 64
      },
      "index": 8359,
      "flags": 1
    }
  ]
}
