{
  "parent": "gamedataTweakDBRecord",
  "name": "gamedataVehicleModel_Record",
  "flags": 66,
  "funcs": [
    {
      "fullName": "EnumComment",
      "shortName": "EnumComment",
      "return": {
        "type": "String",
        "flags": 64
      },
      "index": 3991,
      "flags": 1
    },
    {
      "fullName": "EnumName",
      "shortName": "EnumName",
      "return": {
        "type": "String",
        "flags": 64
      },
      "index": 3990,
      "flags": 1
    },
    {
      "fullName": "Type",
      "shortName": "Type",
      "return": {
        "type": "gamedataVehicleModel",
        "flags": 64
      },
      "index": 3992,
      "flags": 1
    }
  ]
}
