{
  "parent": "IScriptable",
  "name": "inkMenuEventDispatcher",
  "flags": 66,
  "funcs": [
    {
      "fullName": "RegisterToEvent",
      "shortName": "RegisterToEvent",
      "index": 1431,
      "flags": 1,
      "params": [
        {
          "type": "CName",
          "name": "eventName",
          "flags": 128
        },
        {
          "type": "handle:IScriptable",
          "name": "object",
          "flags": 128
        },
        {
          "type": "CName",
          "name": "functionName",
          "flags": 128
        }
      ]
    },
    {
      "fullName": "SpawnAddressedEvent",
      "shortName": "SpawnAddressedEvent",
      "index": 1434,
      "flags": 1,
      "params": [
        {
          "type": "CName",
          "name": "scenario",
          "flags": 128
        },
        {
          "type": "CName",
          "name": "name",
          "flags": 128
        },
        {
          "type": "handle:IScriptable",
          "name": "userData",
          "flags": 1152
        }
      ]
    },
    {
      "fullName": "SpawnEvent",
      "shortName": "SpawnEvent",
      "index": 1433,
      "flags": 1,
      "params": [
        {
          "type": "CName",
          "name": "name",
          "flags": 128
        },
        {
          "type": "handle:IScriptable",
          "name": "userData",
          "flags": 1152
        }
      ]
    },
    {
      "fullName": "UnregisterFromEvent",
      "shortName": "UnregisterFromEvent",
      "index": 1432,
      "flags": 1,
      "params": [
        {
          "type": "CName",
          "name": "eventName",
          "flags": 128
        },
        {
          "type": "handle:IScriptable",
          "name": "object",
          "flags": 128
        },
        {
          "type": "CName",
          "name": "functionName",
          "flags": 128
        }
      ]
    }
  ]
}
