{
  "parent": "ProgressBarSimpleWidgetLogicController",
  "name": "NameplateBarLogicController",
  "flags": 4,
  "props": [
    {
      "type": "whandle:DamagePreviewController",
      "name": "damagePreview",
      "flags": 4297130016
    }
  ],
  "funcs": [
    {
      "fullName": "SetDamagePreview;FloatFloat",
      "shortName": "SetDamagePreview",
      "flags": 516,
      "params": [
        {
          "type": "Float",
          "name": "damage",
          "flags": 128
        },
        {
          "type": "Float",
          "name": "offset",
          "flags": 128
        }
      ]
    },
    {
      "fullName": "SetNameplateBarProgress;FloatBool",
      "shortName": "SetNameplateBarProgress",
      "flags": 516,
      "params": [
        {
          "type": "Float",
          "name": "newValue",
          "flags": 128
        },
        {
          "type": "Bool",
          "name": "silent",
          "flags": 128
        }
      ]
    }
  ]
}
