{
  "parent": "redEvent",
  "name": "entLookAtRemoveEvent",
  "flags": 2,
  "props": [
    {
      "type": "animLookAtRef",
      "name": "lookAtRef",
      "flags": 6627016704
    },
    {
      "type": "Bool",
      "name": "hasOutTransition",
      "flags": 6627016704
    },
    {
      "type": "Float",
      "name": "outTransitionSpeed",
      "flags": 6627016704
    }
  ],
  "funcs": [
    {
      "fullName": "entLookAtRemoveEvent::QueueDelayedRemoveLookatEvent;ScriptExecutionContextLookAtAddEventFloat",
      "shortName": "QueueDelayedRemoveLookatEvent",
      "flags": 518,
      "params": [
        {
          "type": "AIbehaviorScriptExecutionContext",
          "name": "context",
          "flags": 128
        },
        {
          "type": "handle:entLookAtAddEvent",
          "name": "addedBeforeEvent",
          "flags": 128
        },
        {
          "type": "Float",
          "name": "lookAtDeactivationDelay",
          "flags": 128
        }
      ]
    },
    {
      "fullName": "entLookAtRemoveEvent::QueueRemoveLookatEvent;GameObjectLookAtAddEvent",
      "shortName": "QueueRemoveLookatEvent",
      "flags": 518,
      "params": [
        {
          "type": "handle:gameObject",
          "name": "owner",
          "flags": 128
        },
        {
          "type": "handle:entLookAtAddEvent",
          "name": "addedBeforeEvent",
          "flags": 128
        }
      ]
    }
  ]
}
