{
  "parent": "DeviceOperationBase",
  "name": "FactsDeviceOperation",
  "flags": 4,
  "props": [
    {
      "type": "array:SFactOperationData",
      "name": "facts",
      "flags": 6650331169
    }
  ],
  "funcs": [
    {
      "fullName": "Execute;GameObject",
      "shortName": "Execute",
      "flags": 512,
      "params": [
        {
          "type": "whandle:gameObject",
          "name": "owner",
          "flags": 128
        }
      ]
    },
    {
      "fullName": "ResolveFacts;array<SFactOperationData>GameObjectBool",
      "shortName": "ResolveFacts",
      "flags": 132,
      "params": [
        {
          "type": "array:SFactOperationData",
          "name": "factsArg",
          "flags": 128
        },
        {
          "type": "whandle:gameObject",
          "name": "owner",
          "flags": 128
        },
        {
          "type": "Bool",
          "name": "restore",
          "flags": 1152
        }
      ]
    },
    {
      "fullName": "Restore;GameObject",
      "shortName": "Restore",
      "flags": 512,
      "params": [
        {
          "type": "whandle:gameObject",
          "name": "owner",
          "flags": 128
        }
      ]
    }
  ]
}
