{
  "name": "FunctionalTestsResult",
  "flags": 66,
  "props": [
    {
      "type": "FunctionalTestsResultCode",
      "name": "code",
      "flags": 6627016707
    },
    {
      "type": "String",
      "name": "msg",
      "flags": 6627016707
    }
  ],
  "funcs": [
    {
      "fullName": "IsValid",
      "shortName": "IsValid",
      "index": 12823,
      "flags": 3
    },
    {
      "fullName": "Make",
      "shortName": "Make",
      "index": 12820,
      "flags": 3
    },
    {
      "fullName": "MakeValid",
      "shortName": "MakeValid",
      "index": 12821,
      "flags": 3
    },
    {
      "fullName": "SetResult",
      "shortName": "SetResult",
      "index": 12822,
      "flags": 3
    }
  ]
}
