{
  "parent": "gamedataTweakDBRecord",
  "name": "gamedataTPPLookAtPresets_Record",
  "flags": 66,
  "funcs": [
    {
      "fullName": "GetNoWeaponPresetsCount",
      "shortName": "GetNoWeaponPresetsCount",
      "return": {
        "type": "Int32",
        "flags": 64
      },
      "index": 7640,
      "flags": 1
    },
    {
      "fullName": "GetNoWeaponPresetsItem",
      "shortName": "GetNoWeaponPresetsItem",
      "return": {
        "type": "whandle:gamedataLookAtPreset_Record",
        "flags": 64
      },
      "index": 7641,
      "flags": 1,
      "params": [
        {
          "type": "Int32",
          "name": "index",
          "flags": 128
        }
      ]
    },
    {
      "fullName": "GetNoWeaponPresetsItemHandle",
      "shortName": "GetNoWeaponPresetsItemHandle",
      "return": {
        "type": "whandle:gamedataLookAtPreset_Record",
        "flags": 64
      },
      "index": 7642,
      "flags": 1,
      "params": [
        {
          "type": "Int32",
          "name": "index",
          "flags": 128
        }
      ]
    },
    {
      "fullName": "GetReloadPresetsCount",
      "shortName": "GetReloadPresetsCount",
      "return": {
        "type": "Int32",
        "flags": 64
      },
      "index": 7650,
      "flags": 1
    },
    {
      "fullName": "GetReloadPresetsItem",
      "shortName": "GetReloadPresetsItem",
      "return": {
        "type": "whandle:gamedataLookAtPreset_Record",
        "flags": 64
      },
      "index": 7651,
      "flags": 1,
      "params": [
        {
          "type": "Int32",
          "name": "index",
          "flags": 128
        }
      ]
    },
    {
      "fullName": "GetReloadPresetsItemHandle",
      "shortName": "GetReloadPresetsItemHandle",
      "return": {
        "type": "whandle:gamedataLookAtPreset_Record",
        "flags": 64
      },
      "index": 7652,
      "flags": 1,
      "params": [
        {
          "type": "Int32",
          "name": "index",
          "flags": 128
        }
      ]
    },
    {
      "fullName": "GetWeaponReadyPresetsCount",
      "shortName": "GetWeaponReadyPresetsCount",
      "return": {
        "type": "Int32",
        "flags": 64
      },
      "index": 7645,
      "flags": 1
    },
    {
      "fullName": "GetWeaponReadyPresetsItem",
      "shortName": "GetWeaponReadyPresetsItem",
      "return": {
        "type": "whandle:gamedataLookAtPreset_Record",
        "flags": 64
      },
      "index": 7646,
      "flags": 1,
      "params": [
        {
          "type": "Int32",
          "name": "index",
          "flags": 128
        }
      ]
    },
    {
      "fullName": "GetWeaponReadyPresetsItemHandle",
      "shortName": "GetWeaponReadyPresetsItemHandle",
      "return": {
        "type": "whandle:gamedataLookAtPreset_Record",
        "flags": 64
      },
      "index": 7647,
      "flags": 1,
      "params": [
        {
          "type": "Int32",
          "name": "index",
          "flags": 128
        }
      ]
    },
    {
      "fullName": "GetWeaponSafePresetsCount",
      "shortName": "GetWeaponSafePresetsCount",
      "return": {
        "type": "Int32",
        "flags": 64
      },
      "index": 7655,
      "flags": 1
    },
    {
      "fullName": "GetWeaponSafePresetsItem",
      "shortName": "GetWeaponSafePresetsItem",
      "return": {
        "type": "whandle:gamedataLookAtPreset_Record",
        "flags": 64
      },
      "index": 7656,
      "flags": 1,
      "params": [
        {
          "type": "Int32",
          "name": "index",
          "flags": 128
        }
      ]
    },
    {
      "fullName": "GetWeaponSafePresetsItemHandle",
      "shortName": "GetWeaponSafePresetsItemHandle",
      "return": {
        "type": "whandle:gamedataLookAtPreset_Record",
        "flags": 64
      },
      "index": 7657,
      "flags": 1,
      "params": [
        {
          "type": "Int32",
          "name": "index",
          "flags": 128
        }
      ]
    },
    {
      "fullName": "NoWeaponPresets",
      "shortName": "NoWeaponPresets",
      "index": 7639,
      "flags": 1,
      "params": [
        {
          "type": "array:whandle:gamedataLookAtPreset_Record",
          "name": "outList",
          "flags": 640
        }
      ]
    },
    {
      "fullName": "NoWeaponPresetsContains",
      "shortName": "NoWeaponPresetsContains",
      "return": {
        "type": "Bool",
        "flags": 64
      },
      "index": 7643,
      "flags": 1,
      "params": [
        {
          "type": "whandle:gamedataLookAtPreset_Record",
          "name": "item",
          "flags": 128
        }
      ]
    },
    {
      "fullName": "ReloadPresets",
      "shortName": "ReloadPresets",
      "index": 7649,
      "flags": 1,
      "params": [
        {
          "type": "array:whandle:gamedataLookAtPreset_Record",
          "name": "outList",
          "flags": 640
        }
      ]
    },
    {
      "fullName": "ReloadPresetsContains",
      "shortName": "ReloadPresetsContains",
      "return": {
        "type": "Bool",
        "flags": 64
      },
      "index": 7653,
      "flags": 1,
      "params": [
        {
          "type": "whandle:gamedataLookAtPreset_Record",
          "name": "item",
          "flags": 128
        }
      ]
    },
    {
      "fullName": "WeaponReadyPresets",
      "shortName": "WeaponReadyPresets",
      "index": 7644,
      "flags": 1,
      "params": [
        {
          "type": "array:whandle:gamedataLookAtPreset_Record",
          "name": "outList",
          "flags": 640
        }
      ]
    },
    {
      "fullName": "WeaponReadyPresetsContains",
      "shortName": "WeaponReadyPresetsContains",
      "return": {
        "type": "Bool",
        "flags": 64
      },
      "index": 7648,
      "flags": 1,
      "params": [
        {
          "type": "whandle:gamedataLookAtPreset_Record",
          "name": "item",
          "flags": 128
        }
      ]
    },
    {
      "fullName": "WeaponSafePresets",
      "shortName": "WeaponSafePresets",
      "index": 7654,
      "flags": 1,
      "params": [
        {
          "type": "array:whandle:gamedataLookAtPreset_Record",
          "name": "outList",
          "flags": 640
        }
      ]
    },
    {
      "fullName": "WeaponSafePresetsContains",
      "shortName": "WeaponSafePresetsContains",
      "return": {
        "type": "Bool",
        "flags": 64
      },
      "index": 7658,
      "flags": 1,
      "params": [
        {
          "type": "whandle:gamedataLookAtPreset_Record",
          "name": "item",
          "flags": 128
        }
      ]
    }
  ]
}
