{
  "parent": "gameScriptableComponent",
  "name": "gameAINetStateComponent",
  "flags": 66,
  "funcs": [
    {
      "fullName": "GetReplicatedBehaviorState",
      "shortName": "GetReplicatedBehaviorState",
      "return": {
        "type": "Int32",
        "flags": 64
      },
      "index": 9394,
      "flags": 1
    },
    {
      "fullName": "GetReplicatedDefenseMode",
      "shortName": "GetReplicatedDefenseMode",
      "return": {
        "type": "Int32",
        "flags": 64
      },
      "index": 9398,
      "flags": 1
    },
    {
      "fullName": "GetReplicatedHighLevelState",
      "shortName": "GetReplicatedHighLevelState",
      "return": {
        "type": "Int32",
        "flags": 64
      },
      "index": 9386,
      "flags": 1
    },
    {
      "fullName": "GetReplicatedHitReactionModeState",
      "shortName": "GetReplicatedHitReactionModeState",
      "return": {
        "type": "Int32",
        "flags": 64
      },
      "index": 9392,
      "flags": 1
    },
    {
      "fullName": "GetReplicatedLocomotionMode",
      "shortName": "GetReplicatedLocomotionMode",
      "return": {
        "type": "Int32",
        "flags": 64
      },
      "index": 9400,
      "flags": 1
    },
    {
      "fullName": "GetReplicatedPhaseState",
      "shortName": "GetReplicatedPhaseState",
      "return": {
        "type": "Int32",
        "flags": 64
      },
      "index": 9396,
      "flags": 1
    },
    {
      "fullName": "GetReplicatedStanceState",
      "shortName": "GetReplicatedStanceState",
      "return": {
        "type": "Int32",
        "flags": 64
      },
      "index": 9390,
      "flags": 1
    },
    {
      "fullName": "GetReplicatedUpperBodyState",
      "shortName": "GetReplicatedUpperBodyState",
      "return": {
        "type": "Int32",
        "flags": 64
      },
      "index": 9388,
      "flags": 1
    },
    {
      "fullName": "SetReplicatedBehaviorState",
      "shortName": "SetReplicatedBehaviorState",
      "return": {
        "type": "Bool",
        "flags": 64
      },
      "index": 9395,
      "flags": 1,
      "params": [
        {
          "type": "Int32",
          "name": "newState",
          "flags": 128
        }
      ]
    },
    {
      "fullName": "SetReplicatedDefenseMode",
      "shortName": "SetReplicatedDefenseMode",
      "return": {
        "type": "Bool",
        "flags": 64
      },
      "index": 9399,
      "flags": 1,
      "params": [
        {
          "type": "Int32",
          "name": "newState",
          "flags": 128
        }
      ]
    },
    {
      "fullName": "SetReplicatedHighLevelState",
      "shortName": "SetReplicatedHighLevelState",
      "return": {
        "type": "Bool",
        "flags": 64
      },
      "index": 9387,
      "flags": 1,
      "params": [
        {
          "type": "Int32",
          "name": "newState",
          "flags": 128
        }
      ]
    },
    {
      "fullName": "SetReplicatedHitReactionModeState",
      "shortName": "SetReplicatedHitReactionModeState",
      "return": {
        "type": "Bool",
        "flags": 64
      },
      "index": 9393,
      "flags": 1,
      "params": [
        {
          "type": "Int32",
          "name": "newState",
          "flags": 128
        }
      ]
    },
    {
      "fullName": "SetReplicatedLocomotionMode",
      "shortName": "SetReplicatedLocomotionMode",
      "return": {
        "type": "Bool",
        "flags": 64
      },
      "index": 9401,
      "flags": 1,
      "params": [
        {
          "type": "Int32",
          "name": "newState",
          "flags": 128
        }
      ]
    },
    {
      "fullName": "SetReplicatedPhaseState",
      "shortName": "SetReplicatedPhaseState",
      "return": {
        "type": "Bool",
        "flags": 64
      },
      "index": 9397,
      "flags": 1,
      "params": [
        {
          "type": "Int32",
          "name": "newState",
          "flags": 128
        }
      ]
    },
    {
      "fullName": "SetReplicatedStanceState",
      "shortName": "SetReplicatedStanceState",
      "return": {
        "type": "Bool",
        "flags": 64
      },
      "index": 9391,
      "flags": 1,
      "params": [
        {
          "type": "Int32",
          "name": "newState",
          "flags": 128
        }
      ]
    },
    {
      "fullName": "SetReplicatedUpperBodyState",
      "shortName": "SetReplicatedUpperBodyState",
      "return": {
        "type": "Bool",
        "flags": 64
      },
      "index": 9389,
      "flags": 1,
      "params": [
        {
          "type": "Int32",
          "name": "newState",
          "flags": 128
        }
      ]
    }
  ]
}
