{
  "parent": "gamedataTweakDBRecord",
  "name": "gamedataStimPropagation_Record",
  "flags": 66,
  "funcs": [
    {
      "fullName": "Comment",
      "shortName": "Comment",
      "return": {
        "type": "String",
        "flags": 64
      },
      "index": 3989,
      "flags": 1
    },
    {
      "fullName": "EnumName",
      "shortName": "EnumName",
      "return": {
        "type": "CName",
        "flags": 64
      },
      "index": 3990,
      "flags": 1
    },
    {
      "fullName": "Type",
      "shortName": "Type",
      "return": {
        "type": "gamedataStimPropagation",
        "flags": 64
      },
      "index": 3991,
      "flags": 1
    }
  ]
}
