{
  "parent": "gamedataTweakDBRecord",
  "name": "gamedataAINodeMapField_Record",
  "flags": 66,
  "funcs": [
    {
      "fullName": "ForLOD",
      "shortName": "ForLOD",
      "return": {
        "type": "Int32",
        "flags": 64
      },
      "index": 7277,
      "flags": 1
    },
    {
      "fullName": "IsOverriddenBy",
      "shortName": "IsOverriddenBy",
      "return": {
        "type": "whandle:gamedataAIRecord_Record",
        "flags": 64
      },
      "index": 7275,
      "flags": 1
    },
    {
      "fullName": "IsOverriddenByHandle",
      "shortName": "IsOverriddenByHandle",
      "return": {
        "type": "handle:gamedataAIRecord_Record",
        "flags": 64
      },
      "index": 7276,
      "flags": 1
    },
    {
      "fullName": "Node",
      "shortName": "Node",
      "return": {
        "type": "whandle:gamedataAIRecord_Record",
        "flags": 64
      },
      "index": 7273,
      "flags": 1
    },
    {
      "fullName": "NodeHandle",
      "shortName": "NodeHandle",
      "return": {
        "type": "handle:gamedataAIRecord_Record",
        "flags": 64
      },
      "index": 7274,
      "flags": 1
    }
  ]
}
