{
  "parent": "inkWidgetLogicController",
  "name": "gameuiTutorialOverlayLogicController",
  "flags": 2,
  "props": [
    {
      "type": "Bool",
      "name": "hideInMenu",
      "flags": 6627016705
    },
    {
      "type": "Bool",
      "name": "hideOnInput",
      "flags": 6627016704
    },
    {
      "type": "CName",
      "name": "showAnimation",
      "flags": 4297130017
    },
    {
      "type": "CName",
      "name": "hideAnimation",
      "flags": 4297130017
    },
    {
      "type": "handle:inkanimProxy",
      "name": "animProxy",
      "flags": 4431347744
    },
    {
      "type": "whandle:questTutorialManager",
      "name": "tutorialManager",
      "flags": 4297130016
    }
  ],
  "funcs": [
    {
      "fullName": "OnButtonRelease",
      "shortName": "OnButtonRelease",
      "return": {
        "type": "Bool",
        "flags": 64
      },
      "flags": 264,
      "params": [
        {
          "type": "handle:inkPointerEvent",
          "name": "evt",
          "flags": 128
        }
      ]
    },
    {
      "fullName": "OnShowFinished",
      "shortName": "OnShowFinished",
      "return": {
        "type": "Bool",
        "flags": 64
      },
      "flags": 264,
      "params": [
        {
          "type": "handle:inkanimProxy",
          "name": "e",
          "flags": 128
        }
      ]
    },
    {
      "fullName": "OnUninitialize",
      "shortName": "OnUninitialize",
      "return": {
        "type": "Bool",
        "flags": 64
      },
      "flags": 264
    },
    {
      "fullName": "PlayHideAnimation;",
      "shortName": "PlayHideAnimation",
      "return": {
        "type": "handle:inkanimProxy",
        "flags": 64
      },
      "flags": 132
    },
    {
      "fullName": "PlayShowAnimation;",
      "shortName": "PlayShowAnimation",
      "return": {
        "type": "handle:inkanimProxy",
        "flags": 64
      },
      "flags": 132
    },
    {
      "fullName": "SetupTutorialOverlayLogicController;questITutorialManager",
      "shortName": "SetupTutorialOverlayLogicController",
      "flags": 132,
      "params": [
        {
          "type": "handle:questITutorialManager",
          "name": "tutorialManager",
          "flags": 128
        }
      ]
    }
  ]
}
