{
  "parent": "gamedataTweakDBRecord",
  "name": "gamedataArchetypeData_Record",
  "flags": 66,
  "funcs": [
    {
      "fullName": "AbilityGroups",
      "shortName": "AbilityGroups",
      "index": 10868,
      "flags": 1,
      "params": [
        {
          "type": "array:whandle:gamedataGameplayAbilityGroup_Record",
          "name": "outList",
          "flags": 640
        }
      ]
    },
    {
      "fullName": "AbilityGroupsContains",
      "shortName": "AbilityGroupsContains",
      "return": {
        "type": "Bool",
        "flags": 64
      },
      "index": 10872,
      "flags": 1,
      "params": [
        {
          "type": "whandle:gamedataGameplayAbilityGroup_Record",
          "name": "item",
          "flags": 128
        }
      ]
    },
    {
      "fullName": "GetAbilityGroupsCount",
      "shortName": "GetAbilityGroupsCount",
      "return": {
        "type": "Int32",
        "flags": 64
      },
      "index": 10869,
      "flags": 1
    },
    {
      "fullName": "GetAbilityGroupsItem",
      "shortName": "GetAbilityGroupsItem",
      "return": {
        "type": "whandle:gamedataGameplayAbilityGroup_Record",
        "flags": 64
      },
      "index": 10870,
      "flags": 1,
      "params": [
        {
          "type": "Int32",
          "name": "index",
          "flags": 128
        }
      ]
    },
    {
      "fullName": "GetAbilityGroupsItemHandle",
      "shortName": "GetAbilityGroupsItemHandle",
      "return": {
        "type": "handle:gamedataGameplayAbilityGroup_Record",
        "flags": 64
      },
      "index": 10871,
      "flags": 1,
      "params": [
        {
          "type": "Int32",
          "name": "index",
          "flags": 128
        }
      ]
    },
    {
      "fullName": "GetShootingPatternPackagesCount",
      "shortName": "GetShootingPatternPackagesCount",
      "return": {
        "type": "Int32",
        "flags": 64
      },
      "index": 10874,
      "flags": 1
    },
    {
      "fullName": "GetShootingPatternPackagesItem",
      "shortName": "GetShootingPatternPackagesItem",
      "return": {
        "type": "whandle:gamedataAIPatternsPackage_Record",
        "flags": 64
      },
      "index": 10875,
      "flags": 1,
      "params": [
        {
          "type": "Int32",
          "name": "index",
          "flags": 128
        }
      ]
    },
    {
      "fullName": "GetShootingPatternPackagesItemHandle",
      "shortName": "GetShootingPatternPackagesItemHandle",
      "return": {
        "type": "handle:gamedataAIPatternsPackage_Record",
        "flags": 64
      },
      "index": 10876,
      "flags": 1,
      "params": [
        {
          "type": "Int32",
          "name": "index",
          "flags": 128
        }
      ]
    },
    {
      "fullName": "GetStatModifierGroupsCount",
      "shortName": "GetStatModifierGroupsCount",
      "return": {
        "type": "Int32",
        "flags": 64
      },
      "index": 10864,
      "flags": 1
    },
    {
      "fullName": "GetStatModifierGroupsItem",
      "shortName": "GetStatModifierGroupsItem",
      "return": {
        "type": "whandle:gamedataStatModifierGroup_Record",
        "flags": 64
      },
      "index": 10865,
      "flags": 1,
      "params": [
        {
          "type": "Int32",
          "name": "index",
          "flags": 128
        }
      ]
    },
    {
      "fullName": "GetStatModifierGroupsItemHandle",
      "shortName": "GetStatModifierGroupsItemHandle",
      "return": {
        "type": "handle:gamedataStatModifierGroup_Record",
        "flags": 64
      },
      "index": 10866,
      "flags": 1,
      "params": [
        {
          "type": "Int32",
          "name": "index",
          "flags": 128
        }
      ]
    },
    {
      "fullName": "ShootingPatternPackages",
      "shortName": "ShootingPatternPackages",
      "index": 10873,
      "flags": 1,
      "params": [
        {
          "type": "array:whandle:gamedataAIPatternsPackage_Record",
          "name": "outList",
          "flags": 640
        }
      ]
    },
    {
      "fullName": "ShootingPatternPackagesContains",
      "shortName": "ShootingPatternPackagesContains",
      "return": {
        "type": "Bool",
        "flags": 64
      },
      "index": 10877,
      "flags": 1,
      "params": [
        {
          "type": "whandle:gamedataAIPatternsPackage_Record",
          "name": "item",
          "flags": 128
        }
      ]
    },
    {
      "fullName": "StatModifierGroups",
      "shortName": "StatModifierGroups",
      "index": 10863,
      "flags": 1,
      "params": [
        {
          "type": "array:whandle:gamedataStatModifierGroup_Record",
          "name": "outList",
          "flags": 640
        }
      ]
    },
    {
      "fullName": "StatModifierGroupsContains",
      "shortName": "StatModifierGroupsContains",
      "return": {
        "type": "Bool",
        "flags": 64
      },
      "index": 10867,
      "flags": 1,
      "params": [
        {
          "type": "whandle:gamedataStatModifierGroup_Record",
          "name": "item",
          "flags": 128
        }
      ]
    },
    {
      "fullName": "Type",
      "shortName": "Type",
      "return": {
        "type": "whandle:gamedataArchetypeType_Record",
        "flags": 64
      },
      "index": 10861,
      "flags": 1
    },
    {
      "fullName": "TypeHandle",
      "shortName": "TypeHandle",
      "return": {
        "type": "handle:gamedataArchetypeType_Record",
        "flags": 64
      },
      "index": 10862,
      "flags": 1
    }
  ]
}
