{
  "parent": "gameIGameSystem",
  "name": "gameICooldownSystem",
  "flags": 3,
  "funcs": [
    {
      "fullName": "DoesCooldownExist",
      "shortName": "DoesCooldownExist",
      "return": {
        "type": "Bool",
        "flags": 64
      },
      "index": 9508,
      "flags": 1,
      "params": [
        {
          "type": "Int32",
          "name": "id",
          "flags": 128
        }
      ]
    },
    {
      "fullName": "GetCIDByItemID",
      "shortName": "GetCIDByItemID",
      "return": {
        "type": "Int32",
        "flags": 64
      },
      "index": 9511,
      "flags": 1,
      "params": [
        {
          "type": "gameItemID",
          "name": "itemId",
          "flags": 128
        }
      ]
    },
    {
      "fullName": "GetCIDByOwnerAndName",
      "shortName": "GetCIDByOwnerAndName",
      "return": {
        "type": "Int32",
        "flags": 64
      },
      "index": 9509,
      "flags": 1,
      "params": [
        {
          "type": "whandle:entEntity",
          "name": "owner",
          "flags": 128
        },
        {
          "type": "CName",
          "name": "cdName",
          "flags": 128
        }
      ]
    },
    {
      "fullName": "GetCIDByRecord",
      "shortName": "GetCIDByRecord",
      "return": {
        "type": "Int32",
        "flags": 64
      },
      "index": 9510,
      "flags": 1,
      "params": [
        {
          "type": "whandle:entEntity",
          "name": "owner",
          "flags": 128
        },
        {
          "type": "TweakDBID",
          "name": "record",
          "flags": 128
        }
      ]
    },
    {
      "fullName": "Register",
      "shortName": "Register",
      "return": {
        "type": "Int32",
        "flags": 64
      },
      "index": 9512,
      "flags": 1,
      "params": [
        {
          "type": "script_ref:gameRegisterNewCooldownRequest",
          "name": "request",
          "flags": 128
        }
      ]
    },
    {
      "fullName": "RegisterAbility",
      "shortName": "RegisterAbility",
      "return": {
        "type": "Int32",
        "flags": 64
      },
      "index": 9513,
      "flags": 1,
      "params": [
        {
          "type": "script_ref:gameRegisterNewAbilityCooldownRequest",
          "name": "request",
          "flags": 128
        }
      ]
    },
    {
      "fullName": "RegisterFromRecord",
      "shortName": "RegisterFromRecord",
      "return": {
        "type": "Int32",
        "flags": 64
      },
      "index": 9514,
      "flags": 1,
      "params": [
        {
          "type": "script_ref:gameRegisterCooldownFromRecordRequest",
          "name": "request",
          "flags": 128
        }
      ]
    },
    {
      "fullName": "Remove",
      "shortName": "Remove",
      "return": {
        "type": "Bool",
        "flags": 64
      },
      "index": 9515,
      "flags": 1,
      "params": [
        {
          "type": "Int32",
          "name": "id",
          "flags": 128
        }
      ]
    }
  ]
}
