{
  "parent": "gamedataTweakDBRecord",
  "name": "gamedataSmartGunHandlerParams_Record",
  "flags": 66,
  "funcs": [
    {
      "fullName": "Blacklist",
      "shortName": "Blacklist",
      "index": 2811,
      "flags": 1,
      "params": [
        {
          "type": "array:whandle:gamedataAimAssistTargetData_Record",
          "name": "outList",
          "flags": 640
        }
      ]
    },
    {
      "fullName": "BlacklistContains",
      "shortName": "BlacklistContains",
      "return": {
        "type": "Bool",
        "flags": 64
      },
      "index": 2815,
      "flags": 1,
      "params": [
        {
          "type": "whandle:gamedataAimAssistTargetData_Record",
          "name": "item",
          "flags": 128
        }
      ]
    },
    {
      "fullName": "GetBlacklistCount",
      "shortName": "GetBlacklistCount",
      "return": {
        "type": "Int32",
        "flags": 64
      },
      "index": 2812,
      "flags": 1
    },
    {
      "fullName": "GetBlacklistItem",
      "shortName": "GetBlacklistItem",
      "return": {
        "type": "whandle:gamedataAimAssistTargetData_Record",
        "flags": 64
      },
      "index": 2813,
      "flags": 1,
      "params": [
        {
          "type": "Int32",
          "name": "index",
          "flags": 128
        }
      ]
    },
    {
      "fullName": "GetBlacklistItemHandle",
      "shortName": "GetBlacklistItemHandle",
      "return": {
        "type": "handle:gamedataAimAssistTargetData_Record",
        "flags": 64
      },
      "index": 2814,
      "flags": 1,
      "params": [
        {
          "type": "Int32",
          "name": "index",
          "flags": 128
        }
      ]
    }
  ]
}
