{
  "parent": "entIPlacedComponent",
  "name": "gameAudioEmitterComponent",
  "flags": 2,
  "props": [
    {
      "type": "CName",
      "name": "EmitterName",
      "flags": 6627016705
    },
    {
      "type": "audioEntityEmitterContextType",
      "name": "EmitterType",
      "flags": 6627016705
    },
    {
      "type": "gameAudioSyncs",
      "name": "OnAttach",
      "flags": 6627016705
    },
    {
      "type": "gameAudioSyncs",
      "name": "OnDetach",
      "flags": 6627016705
    },
    {
      "type": "Float",
      "name": "updateDistance",
      "flags": 6627016705
    },
    {
      "type": "CName",
      "name": "emitterMetadataName",
      "flags": 6627016705
    },
    {
      "type": "array:CName",
      "name": "Tags",
      "flags": 6631211009
    },
    {
      "type": "redTagList",
      "name": "TagList",
      "flags": 6627016705
    }
  ]
}
