{
  "parent": "inkLeafWidgetReference",
  "name": "inkImageWidgetReference",
  "flags": 2,
  "funcs": [
    {
      "fullName": "GetActiveTextureType",
      "shortName": "GetActiveTextureType",
      "return": {
        "type": "inkTextureType",
        "flags": 64
      },
      "index": 2081,
      "flags": 3,
      "params": [
        {
          "type": "inkImageWidgetReference",
          "name": "self",
          "flags": 128
        }
      ]
    },
    {
      "fullName": "GetContentHAlign",
      "shortName": "GetContentHAlign",
      "index": 2082,
      "flags": 3
    },
    {
      "fullName": "GetContentVAlign",
      "shortName": "GetContentVAlign",
      "index": 2084,
      "flags": 3
    },
    {
      "fullName": "GetTexturePart",
      "shortName": "GetTexturePart",
      "return": {
        "type": "CName",
        "flags": 64
      },
      "index": 2078,
      "flags": 3,
      "params": [
        {
          "type": "inkImageWidgetReference",
          "name": "self",
          "flags": 128
        }
      ]
    },
    {
      "fullName": "IsTexturePartExist",
      "shortName": "IsTexturePartExist",
      "return": {
        "type": "Bool",
        "flags": 64
      },
      "index": 2076,
      "flags": 3,
      "params": [
        {
          "type": "inkImageWidgetReference",
          "name": "self",
          "flags": 128
        },
        {
          "type": "CName",
          "name": "texturePart",
          "flags": 128
        }
      ]
    },
    {
      "fullName": "RequestSetImage",
      "shortName": "RequestSetImage",
      "index": 2086,
      "flags": 3,
      "params": [
        {
          "type": "inkImageWidgetReference",
          "name": "self",
          "flags": 128
        },
        {
          "type": "handle:inkIconReference",
          "name": "iconRefernce",
          "flags": 128
        },
        {
          "type": "whandle:IScriptable",
          "name": "callbackTarget",
          "flags": 1152
        },
        {
          "type": "CName",
          "name": "callbackName",
          "flags": 1152
        }
      ]
    },
    {
      "fullName": "SetActiveTextureType",
      "shortName": "SetActiveTextureType",
      "index": 2080,
      "flags": 3,
      "params": [
        {
          "type": "inkImageWidgetReference",
          "name": "self",
          "flags": 128
        },
        {
          "type": "inkTextureType",
          "name": "activeTextureType",
          "flags": 128
        }
      ]
    },
    {
      "fullName": "SetAtlasResource",
      "shortName": "SetAtlasResource",
      "index": 2079,
      "flags": 3,
      "params": [
        {
          "type": "inkImageWidgetReference",
          "name": "self",
          "flags": 128
        },
        {
          "type": "redResourceReferenceScriptToken",
          "name": "atlasResourcePath",
          "flags": 128
        }
      ]
    },
    {
      "fullName": "SetBrushMirrorType",
      "shortName": "SetBrushMirrorType",
      "index": 2075,
      "flags": 3,
      "params": [
        {
          "type": "inkImageWidgetReference",
          "name": "self",
          "flags": 128
        },
        {
          "type": "inkBrushMirrorType",
          "name": "mirrorType",
          "flags": 128
        }
      ]
    },
    {
      "fullName": "SetBrushTileType",
      "shortName": "SetBrushTileType",
      "index": 2074,
      "flags": 3,
      "params": [
        {
          "type": "inkImageWidgetReference",
          "name": "self",
          "flags": 128
        },
        {
          "type": "inkBrushTileType",
          "name": "tileType",
          "flags": 128
        }
      ]
    },
    {
      "fullName": "SetContentHAlign",
      "shortName": "SetContentHAlign",
      "index": 2083,
      "flags": 3
    },
    {
      "fullName": "SetContentVAlign",
      "shortName": "SetContentVAlign",
      "index": 2085,
      "flags": 3
    },
    {
      "fullName": "SetTexturePart",
      "shortName": "SetTexturePart",
      "return": {
        "type": "Bool",
        "flags": 64
      },
      "index": 2077,
      "flags": 3,
      "params": [
        {
          "type": "inkImageWidgetReference",
          "name": "self",
          "flags": 128
        },
        {
          "type": "CName",
          "name": "texturePart",
          "flags": 128
        }
      ]
    }
  ]
}
