{
  "parent": "inkWidgetLogicController",
  "name": "NewPerksPerkContainerLogicController",
  "flags": 4,
  "props": [
    {
      "type": "gamedataNewPerkSlotType",
      "name": "slotIdentifier",
      "flags": 4297130017
    },
    {
      "type": "inkWidgetReference",
      "name": "perkWidget",
      "flags": 4297130017
    },
    {
      "type": "array:NewPerksWireConnection",
      "name": "wiresConnections",
      "flags": 6583025697
    }
  ],
  "funcs": [
    {
      "fullName": "OnInitialize",
      "shortName": "OnInitialize",
      "return": {
        "type": "Bool",
        "flags": 64
      },
      "flags": 33032
    },
    {
      "fullName": "AddLine;gamedataNewPerkSlotTypescript_ref<array<NewPerk_Record>>",
      "shortName": "AddLine",
      "flags": 33284,
      "params": [
        {
          "type": "gamedataNewPerkSlotType",
          "name": "lineTarget",
          "flags": 128
        },
        {
          "type": "script_ref:array:whandle:gamedataNewPerk_Record",
          "name": "perks",
          "flags": 128
        }
      ]
    },
    {
      "fullName": "AreAnyWiresActive;",
      "shortName": "AreAnyWiresActive",
      "return": {
        "type": "Bool",
        "flags": 64
      },
      "flags": 33284
    },
    {
      "fullName": "AreConnectionWiresVisible;script_ref<NewPerksWireConnection>",
      "shortName": "AreConnectionWiresVisible",
      "return": {
        "type": "Bool",
        "flags": 64
      },
      "flags": 32900,
      "params": [
        {
          "type": "script_ref:NewPerksWireConnection",
          "name": "connection",
          "flags": 128
        }
      ]
    },
    {
      "fullName": "ClearLines;",
      "shortName": "ClearLines",
      "flags": 33284
    },
    {
      "fullName": "ConnectionDependanciesMet;script_ref<NewPerksWireConnection>script_ref<array<NewPerk_Record>>",
      "shortName": "ConnectionDependanciesMet",
      "return": {
        "type": "Bool",
        "flags": 64
      },
      "flags": 32900,
      "params": [
        {
          "type": "script_ref:NewPerksWireConnection",
          "name": "connection",
          "flags": 128
        },
        {
          "type": "script_ref:array:whandle:gamedataNewPerk_Record",
          "name": "perks",
          "flags": 128
        }
      ]
    },
    {
      "fullName": "GetPerkBySlotType;gamedataNewPerkSlotTypescript_ref<array<NewPerk_Record>>",
      "shortName": "GetPerkBySlotType",
      "return": {
        "type": "whandle:gamedataNewPerk_Record",
        "flags": 64
      },
      "flags": 32900,
      "params": [
        {
          "type": "gamedataNewPerkSlotType",
          "name": "slotType",
          "flags": 128
        },
        {
          "type": "script_ref:array:whandle:gamedataNewPerk_Record",
          "name": "perks",
          "flags": 128
        }
      ]
    },
    {
      "fullName": "GetPerkWidget;",
      "shortName": "GetPerkWidget",
      "return": {
        "type": "inkWidgetReference",
        "flags": 64
      },
      "flags": 33284
    },
    {
      "fullName": "GetPerkWidgetController;",
      "shortName": "GetPerkWidgetController",
      "return": {
        "type": "whandle:NewPerksPerkItemLogicController",
        "flags": 64
      },
      "flags": 33284
    },
    {
      "fullName": "GetSlotIdentifier;",
      "shortName": "GetSlotIdentifier",
      "return": {
        "type": "gamedataNewPerkSlotType",
        "flags": 64
      },
      "flags": 33284
    },
    {
      "fullName": "GetWires;gamedataNewPerkSlotType",
      "shortName": "GetWires",
      "return": {
        "type": "array:inkWidgetReference",
        "flags": 64
      },
      "flags": 33284,
      "params": [
        {
          "type": "gamedataNewPerkSlotType",
          "name": "target",
          "flags": 128
        }
      ]
    },
    {
      "fullName": "GetWiresWithTargetBlacklist;script_ref<array<gamedataNewPerkSlotType>>",
      "shortName": "GetWiresWithTargetBlacklist",
      "return": {
        "type": "array:inkWidgetReference",
        "flags": 64
      },
      "flags": 33284,
      "params": [
        {
          "type": "script_ref:array:gamedataNewPerkSlotType",
          "name": "targetBlacklist",
          "flags": 128
        }
      ]
    },
    {
      "fullName": "SetEnabled;Bool",
      "shortName": "SetEnabled",
      "flags": 33284,
      "params": [
        {
          "type": "Bool",
          "name": "value",
          "flags": 128
        }
      ]
    },
    {
      "fullName": "SetLinesState;gamedataNewPerkSlotType",
      "shortName": "SetLinesState",
      "flags": 33284,
      "params": [
        {
          "type": "gamedataNewPerkSlotType",
          "name": "perk",
          "flags": 128
        }
      ]
    },
    {
      "fullName": "SetLinesState;gamedataNewPerkSlotTypeNewPerksWireState",
      "shortName": "SetLinesState",
      "flags": 33284,
      "params": [
        {
          "type": "gamedataNewPerkSlotType",
          "name": "slot",
          "flags": 128
        },
        {
          "type": "NewPerksWireState",
          "name": "state",
          "flags": 128
        }
      ]
    }
  ]
}
