{
  "parent": "IScriptable",
  "name": "PlayerStaminaHelpers",
  "flags": 5,
  "funcs": [
    {
      "fullName": "PlayerStaminaHelpers::GetAirDodgeStaminaCost;",
      "shortName": "GetAirDodgeStaminaCost",
      "return": {
        "type": "Float",
        "flags": 64
      },
      "flags": 518
    },
    {
      "fullName": "PlayerStaminaHelpers::GetBlockStaminaDelay;",
      "shortName": "GetBlockStaminaDelay",
      "return": {
        "type": "Float",
        "flags": 64
      },
      "flags": 518
    },
    {
      "fullName": "PlayerStaminaHelpers::GetDodgeStaminaCost;",
      "shortName": "GetDodgeStaminaCost",
      "return": {
        "type": "Float",
        "flags": 64
      },
      "flags": 518
    },
    {
      "fullName": "PlayerStaminaHelpers::GetExhaustedStatusEffectID;",
      "shortName": "GetExhaustedStatusEffectID",
      "return": {
        "type": "TweakDBID",
        "flags": 64
      },
      "flags": 33286
    },
    {
      "fullName": "PlayerStaminaHelpers::GetJumpStaminaCost;",
      "shortName": "GetJumpStaminaCost",
      "return": {
        "type": "Float",
        "flags": 64
      },
      "flags": 518
    },
    {
      "fullName": "PlayerStaminaHelpers::GetSlideStaminaCost;",
      "shortName": "GetSlideStaminaCost",
      "return": {
        "type": "Float",
        "flags": 64
      },
      "flags": 518
    },
    {
      "fullName": "PlayerStaminaHelpers::GetSprintStaminaCost;",
      "shortName": "GetSprintStaminaCost",
      "return": {
        "type": "Float",
        "flags": 64
      },
      "flags": 518
    },
    {
      "fullName": "PlayerStaminaHelpers::ModifyStamina;PlayerPuppetFloatBool",
      "shortName": "ModifyStamina",
      "flags": 518,
      "params": [
        {
          "type": "handle:PlayerPuppet",
          "name": "player",
          "flags": 128
        },
        {
          "type": "Float",
          "name": "delta",
          "flags": 128
        },
        {
          "type": "Bool",
          "name": "perc",
          "flags": 1152
        }
      ]
    },
    {
      "fullName": "PlayerStaminaHelpers::OnPlayerBlock;PlayerPuppet",
      "shortName": "OnPlayerBlock",
      "flags": 518,
      "params": [
        {
          "type": "handle:PlayerPuppet",
          "name": "player",
          "flags": 128
        }
      ]
    }
  ]
}
