{
  "parent": "redEvent",
  "name": "RewireEvent",
  "flags": 4,
  "props": [
    {
      "type": "entEntityID",
      "name": "ownerID",
      "flags": 4297326624
    },
    {
      "type": "entEntityID",
      "name": "activatorID",
      "flags": 4297326624
    },
    {
      "type": "whandle:gameObject",
      "name": "executor",
      "flags": 4297326624
    },
    {
      "type": "EDrillMachineRewireState",
      "name": "state",
      "flags": 4297326624
    },
    {
      "type": "Bool",
      "name": "sucess",
      "flags": 4297326624
    }
  ]
}
