{
  "parent": "ActionBool",
  "name": "ChestPressWeightHack",
  "flags": 4,
  "funcs": [
    {
      "fullName": "ChestPressWeightHack::IsAvailable;ScriptableDeviceComponentPS",
      "shortName": "IsAvailable",
      "return": {
        "type": "Bool",
        "flags": 64
      },
      "flags": 33286,
      "params": [
        {
          "type": "handle:ScriptableDeviceComponentPS",
          "name": "device",
          "flags": 128
        }
      ]
    },
    {
      "fullName": "ChestPressWeightHack::IsClearanceValid;Clearance",
      "shortName": "IsClearanceValid",
      "return": {
        "type": "Bool",
        "flags": 64
      },
      "flags": 33286,
      "params": [
        {
          "type": "handle:gamedeviceClearance",
          "name": "clearance",
          "flags": 128
        }
      ]
    },
    {
      "fullName": "ChestPressWeightHack::IsContextValid;GetActionsContext",
      "shortName": "IsContextValid",
      "return": {
        "type": "Bool",
        "flags": 64
      },
      "flags": 33286,
      "params": [
        {
          "type": "gameGetActionsContext",
          "name": "context",
          "flags": 128
        }
      ]
    },
    {
      "fullName": "GetInteractionIcon;",
      "shortName": "GetInteractionIcon",
      "return": {
        "type": "whandle:gamedataChoiceCaptionIconPart_Record",
        "flags": 64
      },
      "flags": 8704
    },
    {
      "fullName": "SetProperties;",
      "shortName": "SetProperties",
      "flags": 516
    }
  ]
}
