{
  "parent": "questICharacterConditionType",
  "name": "questCharacterMount_ConditionType",
  "flags": 2,
  "props": [
    {
      "type": "Bool",
      "name": "anyParent",
      "group": "Parent",
      "flags": 6694125573
    },
    {
      "type": "gameEntityReference",
      "name": "parentRef",
      "group": "Parent",
      "flags": 6694125573
    },
    {
      "type": "Bool",
      "name": "parentIsPlayer",
      "group": "Parent",
      "flags": 6694125569
    },
    {
      "type": "Bool",
      "name": "anyChild",
      "group": "Child",
      "flags": 6694125573
    },
    {
      "type": "gameEntityReference",
      "name": "childRef",
      "group": "Child",
      "flags": 6694125573
    },
    {
      "type": "Bool",
      "name": "childIsPlayer",
      "group": "Child",
      "flags": 6694125573
    },
    {
      "type": "questMountConditionType",
      "name": "condition",
      "group": "Conditions",
      "flags": 6694125569
    },
    {
      "type": "Bool",
      "name": "enterAnimationFinished",
      "group": "Conditions",
      "flags": 6694125569
    },
    {
      "type": "gameMountingSlotRole",
      "name": "role",
      "group": "Conditions",
      "flags": 6694125569
    },
    {
      "type": "Bool",
      "name": "usePlayersVehicle",
      "group": "Conditions",
      "flags": 6694125573
    },
    {
      "type": "String",
      "name": "playerVehicleName",
      "group": "Conditions",
      "flags": 6694125573
    },
    {
      "type": "questMountVehicleType",
      "name": "vehicleType",
      "group": "Conditions",
      "flags": 6694125569
    },
    {
      "type": "questMountVehicleOrigin",
      "name": "vehicleOrigin",
      "group": "Conditions",
      "flags": 6694125569
    }
  ]
}
